setup.cfg
setup.py
icenine/__init__.py
icenine.egg-info/PKG-INFO
icenine.egg-info/SOURCES.txt
icenine.egg-info/dependency_links.txt
icenine.egg-info/entry_points.txt
icenine.egg-info/requires.txt
icenine.egg-info/top_level.txt
icenine/contrib/__init__.py
icenine/contrib/keys.py
icenine/contrib/transactions.py
icenine/contrib/words.txt
icenine/contrib/../ui/assets/assets.qrc
icenine/contrib/../ui/assets/images/icon.svg
icenine/core/__init__.py
icenine/core/accounts.py
icenine/core/export.py
icenine/core/metadata.py
icenine/core/seedwords.py
icenine/core/utils.py
icenine/core/../ui/assets/assets.qrc
icenine/core/../ui/assets/images/icon.svg
icenine/ui/__init__.py
icenine/ui/aboutgui.py
icenine/ui/aliasgui.py
icenine/ui/app.py
icenine/ui/assets_rc.py
icenine/ui/gui.py
icenine/ui/models.py
icenine/ui/newaccountgui.py
icenine/ui/passwordgui.py
icenine/ui/transactiongui.py
icenine/ui/transactionwindowgui.py
icenine/ui/assets/assets.qrc
icenine/ui/assets/images/icon.svg
icenine/ui/components/__init__.py
icenine/ui/components/dialogs.py
icenine/ui/components/widgets.py
icenine/ui/components/../assets/assets.qrc
icenine/ui/components/../assets/images/icon.svg
icenine/ui/windows/__init__.py
icenine/ui/windows/alias.py
icenine/ui/windows/transactions.py
icenine/ui/windows/../assets/assets.qrc
icenine/ui/windows/../assets/images/icon.svg